email_builder/__init__.py
email_builder/clients.py
easy_email_builder-1.0.3.dist-info/METADATA
easy_email_builder-1.0.3.dist-info/WHEEL
easy_email_builder-1.0.3.dist-info/top_level.txt
easy_email_builder-1.0.3.dist-info/RECORD
